deezload/.DS_Store
deezload/__init__.py
deezload/base.py
deezload/build.py
deezload/cmd.py
deezload/gui.py
deezload/index.html
deezload/server.py
deezload/settings.py
deezload/utils.py
deezload/static/build_mac.spec
deezload/static/icon.icns
deezload/static/icon.ico
deezload/static/script.js
deezload/static/style.css
deezload-0.2.7.dist-info/METADATA
deezload-0.2.7.dist-info/RECORD
deezload-0.2.7.dist-info/WHEEL
deezload-0.2.7.dist-info/entry_points.txt
deezload-0.2.7.dist-info/top_level.txt
